ai_orchestrator/__init__.py
ai_orchestrator/orchestrator.py
ai_orchestrator-0.1.0.dist-info/LICENSE.md
ai_orchestrator-0.1.0.dist-info/METADATA
ai_orchestrator-0.1.0.dist-info/WHEEL
ai_orchestrator-0.1.0.dist-info/top_level.txt
ai_orchestrator-0.1.0.dist-info/RECORD
